pypaint/__init__.py
pypaint/core.py
pypaint_by_anagh-0.1.0.dist-info/licenses/LICENSE
pypaint_by_anagh-0.1.0.dist-info/METADATA
pypaint_by_anagh-0.1.0.dist-info/WHEEL
pypaint_by_anagh-0.1.0.dist-info/top_level.txt
pypaint_by_anagh-0.1.0.dist-info/RECORD
