Metadata-Version: 2.4
Name: pypaint-by-anagh
Version: 0.1.0
Summary: A simple Python package to draw shapes with turtle graphics.
Author: Your Name
Author-email: anaghbarnwal@hotmail.com
Classifier: Programming Language :: Python :: 3
Classifier: Operating System :: OS Independent
Requires-Python: >=3.6
License-File: LICENSE
Dynamic: author
Dynamic: author-email
Dynamic: classifier
Dynamic: description
Dynamic: description-content-type
Dynamic: license-file
Dynamic: requires-python
Dynamic: summary
